<?xml version="1.0" encoding="UTF-8" ?>

<lookup>
    <register_numbers>
        <register name="r1l">0x0</register>
        <register name="r2l">0x1</register>
        <register name="a1l">0x2</register>
        <register name="a2l">0x3</register>
        <register name="a3l">0x4</register>
        <register name="a4l">0x5</register>
        <register name="s1l">0x6</register>
        <register name="s1l">0x7</register>
        <register name="r1h">0x8</register>
        <register name="r2h">0x9</register>
        <register name="a1h">0xA</register>
        <register name="a2h">0xB</register>
        <register name="a3h">0xC</register>
        <register name="a4h">0xD</register>
        <register name="s1h">0xE</register>
        <register name="s2h">0xF</register>
    </register_numbers>
</lookup>